odoo/addons/pos_order_to_sale_order_sale_financial_risk/README.rst
odoo/addons/pos_order_to_sale_order_sale_financial_risk/__init__.py
odoo/addons/pos_order_to_sale_order_sale_financial_risk/__manifest__.py
odoo/addons/pos_order_to_sale_order_sale_financial_risk/data/demo.xml
odoo/addons/pos_order_to_sale_order_sale_financial_risk/i18n/es.po
odoo/addons/pos_order_to_sale_order_sale_financial_risk/i18n/it.po
odoo/addons/pos_order_to_sale_order_sale_financial_risk/i18n/pos_order_to_sale_order_sale_financial_risk.pot
odoo/addons/pos_order_to_sale_order_sale_financial_risk/models/__init__.py
odoo/addons/pos_order_to_sale_order_sale_financial_risk/models/pos_session.py
odoo/addons/pos_order_to_sale_order_sale_financial_risk/models/sale_order.py
odoo/addons/pos_order_to_sale_order_sale_financial_risk/readme/DESCRIPTION.rst
odoo/addons/pos_order_to_sale_order_sale_financial_risk/static/description/icon.png
odoo/addons/pos_order_to_sale_order_sale_financial_risk/static/description/index.html
odoo/addons/pos_order_to_sale_order_sale_financial_risk/static/img/desktop_table.jpg
odoo/addons/pos_order_to_sale_order_sale_financial_risk/static/src/js/CreateOrderPopup.esm.js
odoo/addons/pos_order_to_sale_order_sale_financial_risk/static/src/js/models.esm.js
odoo/addons/pos_order_to_sale_order_sale_financial_risk/static/src/tests/tours/SaleFinancialRiskPosCompatibility.tour.esm.js
odoo/addons/pos_order_to_sale_order_sale_financial_risk/tests/__init__.py
odoo/addons/pos_order_to_sale_order_sale_financial_risk/tests/test_pos_ui.py
odoo_addon_pos_order_to_sale_order_sale_financial_risk-16.0.1.0.1.2.dist-info/METADATA
odoo_addon_pos_order_to_sale_order_sale_financial_risk-16.0.1.0.1.2.dist-info/WHEEL
odoo_addon_pos_order_to_sale_order_sale_financial_risk-16.0.1.0.1.2.dist-info/top_level.txt
odoo_addon_pos_order_to_sale_order_sale_financial_risk-16.0.1.0.1.2.dist-info/RECORD
